setup.py
JsonAndXmlSerializer.egg-info/PKG-INFO
JsonAndXmlSerializer.egg-info/SOURCES.txt
JsonAndXmlSerializer.egg-info/dependency_links.txt
JsonAndXmlSerializer.egg-info/requires.txt
JsonAndXmlSerializer.egg-info/top_level.txt
Serializer/__init__.py
Serializer/base_serializer.py
Serializer/constants.py
Serializer/dict_serializer.py
Serializer/json_serializer.py
Serializer/serializers_factory.py
Serializer/xml_serializer.py
test/test_constants.py