Metadata-Version: 2.1
Name: JsonAndXmlSerializer
Version: 0.2.1
Summary: Library for class and function serialization
Author: Evgeny Kuznetsov
Author-email: jenakuz2003@gmail.com
Classifier: Intended Audience :: Developers
Classifier: Programming Language :: Python :: 3.10
Classifier: Operating System :: OS Independent
